rs67/__init__.py
rs67/module.py
rs67-0.1.dist-info/METADATA
rs67-0.1.dist-info/WHEEL
rs67-0.1.dist-info/top_level.txt
rs67-0.1.dist-info/RECORD
