Metadata-Version: 2.4
Name: rs67
Version: 0.1
Summary: A custom library with E1 to E9 functions
Author: Your Name
Author-email: gowthaamgowthaam541@gmail.com
Dynamic: author
Dynamic: author-email
Dynamic: summary
